{
  "claim_boundary": "fixture-backed comparison; empirical comparison pipeline; not an empirical validation claim; not a formal proof substitute",
  "comparison_outputs": {
    "dubler_redshift": {
      "metrics": {
        "AIC": -14.740775772248174,
        "BIC": -17.354481411128283,
        "MAE": 0.00895960694857892,
        "R2": 0.9996591548038047,
        "RMSE": 0.00923094413395547,
        "TNE_vs_baseline_note": "Published or fixture baseline remains better or comparable on this small benchmark.",
        "baseline_AIC": -37.654207284227866,
        "baseline_BIC": -38.96106010366792,
        "baseline_MAE": 3.510865350537827e-05,
        "baseline_R2": 0.9999999902011616,
        "baseline_RMSE": 4.949425950466367e-05,
        "baseline_chi_square": 1.1600000000007162,
        "baseline_model": "published_or_fixture_baseline_shift",
        "baseline_weighted_RMSE": 0.7615773105866259,
        "chi_square": 405133141.38148963,
        "data_status": "cached",
        "holdout_feasible": false,
        "normalized_RMSE": 0.00923099664438475,
        "passed_validation": true,
        "residual_mean": -0.0022216599494934448,
        "residual_std": 0.00895960694857892,
        "sign_consistent": true,
        "weighted_RMSE": 14232.588334197853
      },
      "paths": {
        "data": "empirical/outputs/data/dubler_redshift_comparison.csv",
        "figure": "empirical/outputs/figures/dubler_redshift_comparison.png",
        "manifest": "empirical/outputs/manifests/dubler_redshift_manifest.json",
        "metrics": "empirical/outputs/metrics/dubler_redshift_metrics.csv",
        "report": "empirical/outputs/reports/dubler_redshift_report.md",
        "residual_figure": "empirical/outputs/figures/dubler_redshift_residuals.png"
      }
    },
    "eht_horizon": {
      "metrics": {
        "AIC": -3.109123597713289,
        "BIC": -4.336534875473507,
        "MAE": 0.3676233888493883,
        "R2": 0.9988910333419617,
        "RMSE": 0.4112144395934495,
        "TNE_vs_baseline_note": "Mass-distance angular mapping is reported as a finite illustrative proxy; source-specific scaling remains diagnostic only.",
        "baseline_model": "none",
        "central_depression_proxy": 0.09375393008753712,
        "chi_square": 0.13411303381798323,
        "data_status": "cached",
        "horizon_radius_proxy": 4.365858543091713,
        "mean_angular_factor": 0.4373548199470154,
        "normalized_RMSE": 0.013351118168618059,
        "passed_validation": true,
        "residual_mean": -0.12923607120129255,
        "residual_std": 0.39037847434330847,
        "ring_contrast_proxy": 0.6498129758355458,
        "source_specific_RMSE": 7.56568825353835,
        "source_specific_weighted_RMSE": 4.301024542236142,
        "threshold_contour_radius": 2.8027849524570945,
        "weighted_RMSE": 0.18310723211958563
      },
      "paths": {
        "data": "empirical/outputs/data/eht_horizon_comparison.csv",
        "figure": "empirical/outputs/figures/eht_horizon_comparison.png",
        "manifest": "empirical/outputs/manifests/eht_horizon_manifest.json",
        "metrics": "empirical/outputs/metrics/eht_horizon_metrics.csv",
        "report": "empirical/outputs/reports/eht_horizon_report.md",
        "residual_figure": "empirical/outputs/figures/eht_horizon_residuals.png"
      }
    },
    "elastic_pi_ringdown": {
      "metrics": {
        "AIC": -94.42501972459179,
        "BIC": -78.08060958191538,
        "MAE": 0.30602556328260033,
        "R2": 0.16530251461122913,
        "RMSE": 0.37959874289836565,
        "TNE_vs_baseline_note": "Improved preliminary residual fit under the reduced-basis proxy mapping.",
        "baseline_AIC": -97.22324871093389,
        "baseline_BIC": -89.05104363959569,
        "baseline_MAE": 0.32342697747055427,
        "baseline_R2": 0.08554477372111524,
        "baseline_RMSE": 0.39732092338476915,
        "baseline_chi_square": 20.392953342576526,
        "baseline_model": "damped_sinusoid_baseline",
        "baseline_test_RMSE": 0.3714620119574305,
        "baseline_train_RMSE": 0.41389863184221204,
        "baseline_weighted_RMSE": 0.5981397088250139,
        "basis_component_count": 6.0,
        "chi_square": 18.61430323271826,
        "data_status": "fetched",
        "normalized_RMSE": 0.1922230881662322,
        "passed_validation": true,
        "projection_name": "reduced_tne_basis",
        "residual_envelope_RMSE": 0.07442881481097911,
        "residual_mean": 0.0004733455971666575,
        "residual_std": 0.37959844777602175,
        "test_RMSE": 0.3918719724960643,
        "train_RMSE": 0.36544862896967484,
        "weighted_RMSE": 0.5714601677991408,
        "window_duration": 0.259765625,
        "window_start_time_raw": 0.03727531433105469
      },
      "paths": {
        "data": "empirical/outputs/data/elastic_pi_ringdown_comparison.csv",
        "envelope_figure": "empirical/outputs/figures/elastic_pi_ringdown_envelope.png",
        "figure": "empirical/outputs/figures/elastic_pi_ringdown_comparison.png",
        "manifest": "empirical/outputs/manifests/elastic_pi_ringdown_manifest.json",
        "metrics": "empirical/outputs/metrics/elastic_pi_ringdown_metrics.csv",
        "report": "empirical/outputs/reports/elastic_pi_ringdown_report.md",
        "residual_figure": "empirical/outputs/figures/elastic_pi_ringdown_residuals.png"
      }
    },
    "observer_memory": {
      "metrics": {
        "AIC": -110.58280673596282,
        "BIC": -108.40841946606719,
        "MAE": 0.345753407128193,
        "R2": 0.0014652065108782253,
        "RMSE": 0.4206216300949059,
        "TNE_vs_baseline_note": "Weak explanatory power remains possible even when residual envelopes are smoother.",
        "baseline_model": "none",
        "chi_square": 26.102142553291383,
        "data_status": "fetched",
        "normalized_RMSE": 0.21315768063093307,
        "passed_validation": true,
        "residual_envelope_mean": 0.4055689482418678,
        "residual_mean": -0.011569278592201934,
        "residual_std": 0.42046249237780037,
        "weighted_RMSE": 0.633696633963595
      },
      "paths": {
        "data": "empirical/outputs/data/observer_memory_comparison.csv",
        "figure": "empirical/outputs/figures/observer_memory_comparison.png",
        "manifest": "empirical/outputs/manifests/observer_memory_manifest.json",
        "metrics": "empirical/outputs/metrics/observer_memory_metrics.csv",
        "report": "empirical/outputs/reports/observer_memory_report.md"
      }
    },
    "spiral_rotation": {
      "metrics": {
        "AIC": -274.09169213777017,
        "BIC": -255.87836318564172,
        "MAE": 0.09439257942868998,
        "R2": 0.5541555720502259,
        "RMSE": 0.1333836602551069,
        "TNE_vs_baseline_note": "Improved preliminary residual fit under the implemented multi-galaxy proxy mapping.",
        "angular_momentum_drift": -0.641949744126786,
        "arm_asymmetry_index": 0.5864041153070092,
        "baseline_AIC": -280.4856700276739,
        "baseline_BIC": -275.9323377896418,
        "baseline_MAE": 0.09843089286227866,
        "baseline_R2": 0.5180542802371275,
        "baseline_RMSE": 0.13867878342355602,
        "baseline_chi_square": 15951.741531867629,
        "baseline_model": "multi_galaxy_baseline_family",
        "baseline_weighted_RMSE": 14.884621786272694,
        "chi_square": 4627.140813674527,
        "data_status": "fetched",
        "density_arm_contrast": 2.930627796275457,
        "elastic_tension_max": 1.0,
        "flat_baseline_RMSE": 0.18644023766915546,
        "galaxy_count": 3.0,
        "linear_baseline_RMSE": 0.13867878342355602,
        "mode_2_amplitude": 0.5942853416141742,
        "mode_3_amplitude": 0.6542964755216069,
        "normalized_RMSE": 0.15792786319779026,
        "passed_validation": true,
        "pitch_angle_proxy": 2.6310798498451615,
        "radial_concentration": 0.6523310994199191,
        "residual_mean": 0.0006013991403827542,
        "residual_std": 0.13338230445648977,
        "spiral_order_parameter": 0.5942853416141742,
        "weighted_RMSE": 8.016598071150158
      },
      "paths": {
        "data": "empirical/outputs/data/spiral_rotation_comparison.csv",
        "figure": "empirical/outputs/figures/spiral_rotation_comparison.png",
        "manifest": "empirical/outputs/manifests/spiral_rotation_manifest.json",
        "metrics": "empirical/outputs/metrics/spiral_rotation_metrics.csv",
        "morphology_figure": "empirical/outputs/figures/spiral_morphology_comparison.png",
        "report": "empirical/outputs/reports/spiral_rotation_report.md",
        "residual_figure": "empirical/outputs/figures/spiral_rotation_residuals.png"
      }
    }
  },
  "limitations": "Comparisons remain preliminary repository-linked support artifacts. Residual comparisons do not establish empirical validation.",
  "registry_status": {
    "eht_observables": "cached",
    "galaxy_rotation": "fetched",
    "ligo_ringdown": "fetched",
    "ligo_waveforms": "fetched",
    "redshift_clock": "cached"
  },
  "run_mode": {
    "audit": true,
    "dataset": "all",
    "fetch": false,
    "improve": false,
    "offline": false,
    "parameter_sweep_level": "standard",
    "quick": false,
    "use_fixtures": true
  },
  "summary_outputs": {
    "manifest": "empirical/outputs/manifests/empirical_comparison_metadata.json",
    "metrics": "empirical/outputs/metrics/empirical_comparison_summary.csv",
    "report": "empirical/outputs/reports/empirical_comparison_summary.md"
  }
}